geomi/__init__.py
geomi/ndim/__init__.py
geomi/ndim/mod1.py
geomi/ndim/mod2.py
geomi/planar/__init__.py
geomi/planar/mod1.py
geomi/planar/mod2.py
geomi/solid/__init__.py
geomi/solid/mod1.py
geomi/solid/mod2.py
geomi/utils/__init__.py
geomi/utils/algos/__init__.py
geomi/utils/algos/mod1.py
geomi/utils/algos/mod2.py
geomi/utils/plotter/__init__.py
geomi/utils/plotter/mod1.py
geomi/utils/plotter/mod2.py
geomi-0.0.0.dev0.dist-info/DESCRIPTION.rst
geomi-0.0.0.dev0.dist-info/LICENSE.txt
geomi-0.0.0.dev0.dist-info/METADATA
geomi-0.0.0.dev0.dist-info/RECORD
geomi-0.0.0.dev0.dist-info/WHEEL
geomi-0.0.0.dev0.dist-info/metadata.json
geomi-0.0.0.dev0.dist-info/top_level.txt
