Metadata-Version: 2.0
Name: geomi
Version: 0.0.0.dev0
Summary: Planar, solid and higher dimensional geometry.
Home-page: https://geomi.readthedocs.io/
Author: Arvind Padmanabhan
Author-email: arvindpdmn@gmail.com
License: MIT
Keywords: geometry,algorithm,plot,graph
Platform: UNKNOWN
Classifier: Development Status :: 5 - Production/Stable
Classifier: Intended Audience :: Science/Research
Classifier: Natural Language :: English
Classifier: License :: OSI Approved :: MIT License
Classifier: Operating System :: OS Independent
Classifier: Programming Language :: Python
Classifier: Programming Language :: Python :: 2
Classifier: Programming Language :: Python :: 2.7
Classifier: Programming Language :: Python :: 3
Classifier: Programming Language :: Python :: 3.5
Classifier: Topic :: Scientific/Engineering
Classifier: Topic :: Scientific/Engineering :: Mathematics
